Metadata-Version: 1.0
Name: arsooo-distributions
Version: 0.1
Summary: Gaussian distributions
Home-page: UNKNOWN
Author: Arsalan Khan
Author-email: arsalansunny.kha@gmail.com
License: UNKNOWN
Platform: UNKNOWN
